[
  {
    "id": 7548986,
    "node_id": "MDEwOlJlcG9zaXRvcnk3NTQ4OTg2",
    "name": "framework",
    "full_name": "laravel/framework",
    "private": false,
    "owner": {
      "login": "laravel",
      "id": 958072,
      "node_id": "MDEyOk9yZ2FuaXphdGlvbjk1ODA3Mg==",
      "avatar_url": "https://avatars.githubusercontent.com/u/958072?v=4",
      "gravatar_id": "",
      "url": "https://api.github.com/users/laravel",
      "html_url": "https://github.com/laravel",
      "followers_url": "https://api.github.com/users/laravel/followers",
      "following_url": "https://api.github.com/users/laravel/following{/other_user}",
      "gists_url": "https://api.github.com/users/laravel/gists{/gist_id}",
      "starred_url": "https://api.github.com/users/laravel/starred{/owner}{/repo}",
      "subscriptions_url": "https://api.github.com/users/laravel/subscriptions",
      "organizations_url": "https://api.github.com/users/laravel/orgs",
      "repos_url": "https://api.github.com/users/laravel/repos",
      "events_url": "https://api.github.com/users/laravel/events{/privacy}",
      "received_events_url": "https://api.github.com/users/laravel/received_events",
      "type": "Organization",
      "site_admin": false
    },
    "html_url": "https://github.com/laravel/framework",
    "description": "The Laravel Framework.",
    "fork": false,
    "url": "https://api.github.com/repos/laravel/framework",
    "forks_url": "https://api.github.com/repos/laravel/framework/forks",
    "keys_url": "https://api.github.com/repos/laravel/framework/keys{/key_id}",
    "collaborators_url": "https://api.github.com/repos/laravel/framework/collaborators{/collaborator}",
    "teams_url": "https://api.github.com/repos/laravel/framework/teams",
    "hooks_url": "https://api.github.com/repos/laravel/framework/hooks",
    "issue_events_url": "https://api.github.com/repos/laravel/framework/issues/events{/number}",
    "events_url": "https://api.github.com/repos/laravel/framework/events",
    "assignees_url": "https://api.github.com/repos/laravel/framework/assignees{/user}",
    "branches_url": "https://api.github.com/repos/laravel/framework/branches{/branch}",
    "tags_url": "https://api.github.com/repos/laravel/framework/tags",
    "blobs_url": "https://api.github.com/repos/laravel/framework/git/blobs{/sha}",
    "git_tags_url": "https://api.github.com/repos/laravel/framework/git/tags{/sha}",
    "git_refs_url": "https://api.github.com/repos/laravel/framework/git/refs{/sha}",
    "trees_url": "https://api.github.com/repos/laravel/framework/git/trees{/sha}",
    "statuses_url": "https://api.github.com/repos/laravel/framework/statuses/{sha}",
    "languages_url": "https://api.github.com/repos/laravel/framework/languages",
    "stargazers_url": "https://api.github.com/repos/laravel/framework/stargazers",
    "contributors_url": "https://api.github.com/repos/laravel/framework/contributors",
    "subscribers_url": "https://api.github.com/repos/laravel/framework/subscribers",
    "subscription_url": "https://api.github.com/repos/laravel/framework/subscription",
    "commits_url": "https://api.github.com/repos/laravel/framework/commits{/sha}",
    "git_commits_url": "https://api.github.com/repos/laravel/framework/git/commits{/sha}",
    "comments_url": "https://api.github.com/repos/laravel/framework/comments{/number}",
    "issue_comment_url": "https://api.github.com/repos/laravel/framework/issues/comments{/number}",
    "contents_url": "https://api.github.com/repos/laravel/framework/contents/{+path}",
    "compare_url": "https://api.github.com/repos/laravel/framework/compare/{base}...{head}",
    "merges_url": "https://api.github.com/repos/laravel/framework/merges",
    "archive_url": "https://api.github.com/repos/laravel/framework/{archive_format}{/ref}",
    "downloads_url": "https://api.github.com/repos/laravel/framework/downloads",
    "issues_url": "https://api.github.com/repos/laravel/framework/issues{/number}",
    "pulls_url": "https://api.github.com/repos/laravel/framework/pulls{/number}",
    "milestones_url": "https://api.github.com/repos/laravel/framework/milestones{/number}",
    "notifications_url": "https://api.github.com/repos/laravel/framework/notifications{?since,all,participating}",
    "labels_url": "https://api.github.com/repos/laravel/framework/labels{/name}",
    "releases_url": "https://api.github.com/repos/laravel/framework/releases{/id}",
    "deployments_url": "https://api.github.com/repos/laravel/framework/deployments",
    "created_at": "2013-01-10T21:27:28Z",
    "updated_at": "2022-05-26T12:57:22Z",
    "pushed_at": "2022-05-26T14:38:15Z",
    "git_url": "git://github.com/laravel/framework.git",
    "ssh_url": "git@github.com:laravel/framework.git",
    "clone_url": "https://github.com/laravel/framework.git",
    "svn_url": "https://github.com/laravel/framework",
    "homepage": "https://laravel.com",
    "size": 66624,
    "stargazers_count": 27037,
    "watchers_count": 27037,
    "language": "PHP",
    "has_issues": true,
    "has_projects": false,
    "has_downloads": true,
    "has_wiki": false,
    "has_pages": false,
    "forks_count": 9226,
    "mirror_url": null,
    "archived": false,
    "disabled": false,
    "open_issues_count": 7,
    "license": {
      "key": "mit",
      "name": "MIT License",
      "spdx_id": "MIT",
      "url": "https://api.github.com/licenses/mit",
      "node_id": "MDc6TGljZW5zZTEz"
    },
    "allow_forking": true,
    "is_template": false,
    "topics": [
      "framework",
      "laravel",
      "php"
    ],
    "visibility": "public",
    "forks": 9226,
    "open_issues": 7,
    "watchers": 27037,
    "default_branch": "9.x",
    "permissions": {
      "admin": false,
      "maintain": false,
      "push": false,
      "triage": false,
      "pull": true
    },
    "temp_clone_token": "",
    "organization": {
      "login": "laravel",
      "id": 958072,
      "node_id": "MDEyOk9yZ2FuaXphdGlvbjk1ODA3Mg==",
      "avatar_url": "https://avatars.githubusercontent.com/u/958072?v=4",
      "gravatar_id": "",
      "url": "https://api.github.com/users/laravel",
      "html_url": "https://github.com/laravel",
      "followers_url": "https://api.github.com/users/laravel/followers",
      "following_url": "https://api.github.com/users/laravel/following{/other_user}",
      "gists_url": "https://api.github.com/users/laravel/gists{/gist_id}",
      "starred_url": "https://api.github.com/users/laravel/starred{/owner}{/repo}",
      "subscriptions_url": "https://api.github.com/users/laravel/subscriptions",
      "organizations_url": "https://api.github.com/users/laravel/orgs",
      "repos_url": "https://api.github.com/users/laravel/repos",
      "events_url": "https://api.github.com/users/laravel/events{/privacy}",
      "received_events_url": "https://api.github.com/users/laravel/received_events",
      "type": "Organization",
      "site_admin": false
    },
    "network_count": 9226,
    "subscribers_count": 1020
  },
  {
    "id": 47127359,
    "node_id": "MDEwOlJlcG9zaXRvcnk0NzEyNzM1OQ==",
    "name": "socialite",
    "full_name": "overtrue/socialite",
    "private": false,
    "owner": {
      "login": "overtrue",
      "id": 1472352,
      "node_id": "MDQ6VXNlcjE0NzIzNTI=",
      "avatar_url": "https://avatars.githubusercontent.com/u/1472352?v=4",
      "gravatar_id": "",
      "url": "https://api.github.com/users/overtrue",
      "html_url": "https://github.com/overtrue",
      "followers_url": "https://api.github.com/users/overtrue/followers",
      "following_url": "https://api.github.com/users/overtrue/following{/other_user}",
      "gists_url": "https://api.github.com/users/overtrue/gists{/gist_id}",
      "starred_url": "https://api.github.com/users/overtrue/starred{/owner}{/repo}",
      "subscriptions_url": "https://api.github.com/users/overtrue/subscriptions",
      "organizations_url": "https://api.github.com/users/overtrue/orgs",
      "repos_url": "https://api.github.com/users/overtrue/repos",
      "events_url": "https://api.github.com/users/overtrue/events{/privacy}",
      "received_events_url": "https://api.github.com/users/overtrue/received_events",
      "type": "User",
      "site_admin": false
    },
    "html_url": "https://github.com/overtrue/socialite",
    "description": "Socialite is an OAuth2 Authentication tool. It is inspired by laravel/socialite, you can easily use it without Laravel.",
    "fork": false,
    "url": "https://api.github.com/repos/overtrue/socialite",
    "forks_url": "https://api.github.com/repos/overtrue/socialite/forks",
    "keys_url": "https://api.github.com/repos/overtrue/socialite/keys{/key_id}",
    "collaborators_url": "https://api.github.com/repos/overtrue/socialite/collaborators{/collaborator}",
    "teams_url": "https://api.github.com/repos/overtrue/socialite/teams",
    "hooks_url": "https://api.github.com/repos/overtrue/socialite/hooks",
    "issue_events_url": "https://api.github.com/repos/overtrue/socialite/issues/events{/number}",
    "events_url": "https://api.github.com/repos/overtrue/socialite/events",
    "assignees_url": "https://api.github.com/repos/overtrue/socialite/assignees{/user}",
    "branches_url": "https://api.github.com/repos/overtrue/socialite/branches{/branch}",
    "tags_url": "https://api.github.com/repos/overtrue/socialite/tags",
    "blobs_url": "https://api.github.com/repos/overtrue/socialite/git/blobs{/sha}",
    "git_tags_url": "https://api.github.com/repos/overtrue/socialite/git/tags{/sha}",
    "git_refs_url": "https://api.github.com/repos/overtrue/socialite/git/refs{/sha}",
    "trees_url": "https://api.github.com/repos/overtrue/socialite/git/trees{/sha}",
    "statuses_url": "https://api.github.com/repos/overtrue/socialite/statuses/{sha}",
    "languages_url": "https://api.github.com/repos/overtrue/socialite/languages",
    "stargazers_url": "https://api.github.com/repos/overtrue/socialite/stargazers",
    "contributors_url": "https://api.github.com/repos/overtrue/socialite/contributors",
    "subscribers_url": "https://api.github.com/repos/overtrue/socialite/subscribers",
    "subscription_url": "https://api.github.com/repos/overtrue/socialite/subscription",
    "commits_url": "https://api.github.com/repos/overtrue/socialite/commits{/sha}",
    "git_commits_url": "https://api.github.com/repos/overtrue/socialite/git/commits{/sha}",
    "comments_url": "https://api.github.com/repos/overtrue/socialite/comments{/number}",
    "issue_comment_url": "https://api.github.com/repos/overtrue/socialite/issues/comments{/number}",
    "contents_url": "https://api.github.com/repos/overtrue/socialite/contents/{+path}",
    "compare_url": "https://api.github.com/repos/overtrue/socialite/compare/{base}...{head}",
    "merges_url": "https://api.github.com/repos/overtrue/socialite/merges",
    "archive_url": "https://api.github.com/repos/overtrue/socialite/{archive_format}{/ref}",
    "downloads_url": "https://api.github.com/repos/overtrue/socialite/downloads",
    "issues_url": "https://api.github.com/repos/overtrue/socialite/issues{/number}",
    "pulls_url": "https://api.github.com/repos/overtrue/socialite/pulls{/number}",
    "milestones_url": "https://api.github.com/repos/overtrue/socialite/milestones{/number}",
    "notifications_url": "https://api.github.com/repos/overtrue/socialite/notifications{?since,all,participating}",
    "labels_url": "https://api.github.com/repos/overtrue/socialite/labels{/name}",
    "releases_url": "https://api.github.com/repos/overtrue/socialite/releases{/id}",
    "deployments_url": "https://api.github.com/repos/overtrue/socialite/deployments",
    "created_at": "2015-11-30T15:21:29Z",
    "updated_at": "2022-05-26T13:59:57Z",
    "pushed_at": "2022-05-14T13:53:23Z",
    "git_url": "git://github.com/overtrue/socialite.git",
    "ssh_url": "git@github.com:overtrue/socialite.git",
    "clone_url": "https://github.com/overtrue/socialite.git",
    "svn_url": "https://github.com/overtrue/socialite",
    "homepage": "",
    "size": 340,
    "stargazers_count": 1171,
    "watchers_count": 1171,
    "language": "PHP",
    "has_issues": true,
    "has_projects": true,
    "has_downloads": true,
    "has_wiki": true,
    "has_pages": false,
    "forks_count": 221,
    "mirror_url": null,
    "archived": false,
    "disabled": false,
    "open_issues_count": 3,
    "license": {
      "key": "mit",
      "name": "MIT License",
      "spdx_id": "MIT",
      "url": "https://api.github.com/licenses/mit",
      "node_id": "MDc6TGljZW5zZTEz"
    },
    "allow_forking": true,
    "is_template": false,
    "topics": [
      "alipay",
      "baidu",
      "dingtalk",
      "douban",
      "douyin",
      "facebook",
      "feishu",
      "google",
      "laravel",
      "linkedin",
      "login",
      "oauth",
      "oauth2",
      "oauth2-authentication",
      "qq",
      "social-login",
      "socialite",
      "taobao",
      "wechat",
      "weibo"
    ],
    "visibility": "public",
    "forks": 221,
    "open_issues": 3,
    "watchers": 1171,
    "default_branch": "master",
    "permissions": {
      "admin": true,
      "maintain": true,
      "push": true,
      "triage": true,
      "pull": true
    },
    "temp_clone_token": "",
    "allow_squash_merge": true,
    "allow_merge_commit": true,
    "allow_rebase_merge": true,
    "allow_auto_merge": false,
    "delete_branch_on_merge": false,
    "allow_update_branch": false,
    "network_count": 221,
    "subscribers_count": 33
  },
  {
    "id": 184188307,
    "node_id": "MDEwOlJlcG9zaXRvcnkxODQxODgzMDc=",
    "name": "laravel-favorite",
    "full_name": "overtrue/laravel-favorite",
    "private": false,
    "owner": {
      "login": "overtrue",
      "id": 1472352,
      "node_id": "MDQ6VXNlcjE0NzIzNTI=",
      "avatar_url": "https://avatars.githubusercontent.com/u/1472352?v=4",
      "gravatar_id": "",
      "url": "https://api.github.com/users/overtrue",
      "html_url": "https://github.com/overtrue",
      "followers_url": "https://api.github.com/users/overtrue/followers",
      "following_url": "https://api.github.com/users/overtrue/following{/other_user}",
      "gists_url": "https://api.github.com/users/overtrue/gists{/gist_id}",
      "starred_url": "https://api.github.com/users/overtrue/starred{/owner}{/repo}",
      "subscriptions_url": "https://api.github.com/users/overtrue/subscriptions",
      "organizations_url": "https://api.github.com/users/overtrue/orgs",
      "repos_url": "https://api.github.com/users/overtrue/repos",
      "events_url": "https://api.github.com/users/overtrue/events{/privacy}",
      "received_events_url": "https://api.github.com/users/overtrue/received_events",
      "type": "User",
      "site_admin": false
    },
    "html_url": "https://github.com/overtrue/laravel-favorite",
    "description": ":heart: User favorite feature for Laravel Application.",
    "fork": false,
    "url": "https://api.github.com/repos/overtrue/laravel-favorite",
    "forks_url": "https://api.github.com/repos/overtrue/laravel-favorite/forks",
    "keys_url": "https://api.github.com/repos/overtrue/laravel-favorite/keys{/key_id}",
    "collaborators_url": "https://api.github.com/repos/overtrue/laravel-favorite/collaborators{/collaborator}",
    "teams_url": "https://api.github.com/repos/overtrue/laravel-favorite/teams",
    "hooks_url": "https://api.github.com/repos/overtrue/laravel-favorite/hooks",
    "issue_events_url": "https://api.github.com/repos/overtrue/laravel-favorite/issues/events{/number}",
    "events_url": "https://api.github.com/repos/overtrue/laravel-favorite/events",
    "assignees_url": "https://api.github.com/repos/overtrue/laravel-favorite/assignees{/user}",
    "branches_url": "https://api.github.com/repos/overtrue/laravel-favorite/branches{/branch}",
    "tags_url": "https://api.github.com/repos/overtrue/laravel-favorite/tags",
    "blobs_url": "https://api.github.com/repos/overtrue/laravel-favorite/git/blobs{/sha}",
    "git_tags_url": "https://api.github.com/repos/overtrue/laravel-favorite/git/tags{/sha}",
    "git_refs_url": "https://api.github.com/repos/overtrue/laravel-favorite/git/refs{/sha}",
    "trees_url": "https://api.github.com/repos/overtrue/laravel-favorite/git/trees{/sha}",
    "statuses_url": "https://api.github.com/repos/overtrue/laravel-favorite/statuses/{sha}",
    "languages_url": "https://api.github.com/repos/overtrue/laravel-favorite/languages",
    "stargazers_url": "https://api.github.com/repos/overtrue/laravel-favorite/stargazers",
    "contributors_url": "https://api.github.com/repos/overtrue/laravel-favorite/contributors",
    "subscribers_url": "https://api.github.com/repos/overtrue/laravel-favorite/subscribers",
    "subscription_url": "https://api.github.com/repos/overtrue/laravel-favorite/subscription",
    "commits_url": "https://api.github.com/repos/overtrue/laravel-favorite/commits{/sha}",
    "git_commits_url": "https://api.github.com/repos/overtrue/laravel-favorite/git/commits{/sha}",
    "comments_url": "https://api.github.com/repos/overtrue/laravel-favorite/comments{/number}",
    "issue_comment_url": "https://api.github.com/repos/overtrue/laravel-favorite/issues/comments{/number}",
    "contents_url": "https://api.github.com/repos/overtrue/laravel-favorite/contents/{+path}",
    "compare_url": "https://api.github.com/repos/overtrue/laravel-favorite/compare/{base}...{head}",
    "merges_url": "https://api.github.com/repos/overtrue/laravel-favorite/merges",
    "archive_url": "https://api.github.com/repos/overtrue/laravel-favorite/{archive_format}{/ref}",
    "downloads_url": "https://api.github.com/repos/overtrue/laravel-favorite/downloads",
    "issues_url": "https://api.github.com/repos/overtrue/laravel-favorite/issues{/number}",
    "pulls_url": "https://api.github.com/repos/overtrue/laravel-favorite/pulls{/number}",
    "milestones_url": "https://api.github.com/repos/overtrue/laravel-favorite/milestones{/number}",
    "notifications_url": "https://api.github.com/repos/overtrue/laravel-favorite/notifications{?since,all,participating}",
    "labels_url": "https://api.github.com/repos/overtrue/laravel-favorite/labels{/name}",
    "releases_url": "https://api.github.com/repos/overtrue/laravel-favorite/releases{/id}",
    "deployments_url": "https://api.github.com/repos/overtrue/laravel-favorite/deployments",
    "created_at": "2019-04-30T03:54:26Z",
    "updated_at": "2022-05-20T15:25:33Z",
    "pushed_at": "2022-04-01T02:32:34Z",
    "git_url": "git://github.com/overtrue/laravel-favorite.git",
    "ssh_url": "git@github.com:overtrue/laravel-favorite.git",
    "clone_url": "https://github.com/overtrue/laravel-favorite.git",
    "svn_url": "https://github.com/overtrue/laravel-favorite",
    "homepage": "",
    "size": 126,
    "stargazers_count": 207,
    "watchers_count": 207,
    "language": "PHP",
    "has_issues": true,
    "has_projects": false,
    "has_downloads": true,
    "has_wiki": true,
    "has_pages": false,
    "forks_count": 34,
    "mirror_url": null,
    "archived": false,
    "disabled": false,
    "open_issues_count": 0,
    "license": null,
    "allow_forking": true,
    "is_template": false,
    "topics": [
      "favorites",
      "followers",
      "following",
      "laravel-favorite",
      "user-relations"
    ],
    "visibility": "public",
    "forks": 34,
    "open_issues": 0,
    "watchers": 207,
    "default_branch": "master",
    "permissions": {
      "admin": true,
      "maintain": true,
      "push": true,
      "triage": true,
      "pull": true
    },
    "temp_clone_token": "",
    "allow_squash_merge": true,
    "allow_merge_commit": true,
    "allow_rebase_merge": true,
    "allow_auto_merge": false,
    "delete_branch_on_merge": false,
    "allow_update_branch": false,
    "network_count": 34,
    "subscribers_count": 4
  }
]